{
  "file_hash": "0d1976a774273f6244ebd9cde13904e0",
  "file_name": "29_A-諾貝爾眼科半年約2025年度每月明細表.xlsx",
  "rid": "29",
  "ai_interpretations": [
    {
      "sheet": "年約",
      "row_idx": 5,
      "col_idx": -1,
      "date": "",
      "ad_name": "",
      "spots": 720,
      "seconds": null,
      "confidence": "medium",
      "rule_used": "unit_val_extraction_v29",
      "reason": "Row 6: 發現重複數值 720 (出現 10 次), level=L2, bonus=1",
      "raw_value": 720,
      "raw_row": [
        NaN,
        "購買\n7.5組",
        "全家-北北基 1571間",
        NaN,
        "每日24檔，執行15天",
        360,
        "每日24檔，執行30天",
        720,
        "每日24檔，執行30天",
        720,
        "每日24檔，執行30天",
        720,
        "每日24檔，執行30天",
        720,
        NaN,
        NaN,
        "每日24檔，執行30天",
        720,
        "每日24檔，執行30天",
        720,
        "每日24檔，執行30天",
        720,
        NaN,
        NaN,
        5400,
        "※ 走期及檔次\n運用建議\n可再視當時情況調整\n",
        "5月",
        360,
        "排0.5月聲量"
      ]
    },
    {
      "sheet": "年約",
      "row_idx": 6,
      "col_idx": -1,
      "date": "",
      "ad_name": "",
      "spots": 720,
      "seconds": null,
      "confidence": "medium",
      "rule_used": "unit_val_extraction_v29",
      "reason": "Row 7: 發現重複數值 720 (出現 10 次), level=L2, bonus=1",
      "raw_value": 720,
      "raw_row": [
        NaN,
        NaN,
        "全家-桃竹苗 705間",
        NaN,
        "每日24檔，執行15天",
        360,
        "每日24檔，執行30天",
        720,
        "每日24檔，執行30天",
        720,
        "每日24檔，執行30天",
        720,
        "每日24檔，執行30天",
        720,
        NaN,
        NaN,
        "每日24檔，執行30天",
        720,
        "每日24檔，執行30天",
        720,
        "每日24檔，執行30天",
        720,
        NaN,
        NaN,
        5400,
        NaN,
        "6月",
        1080,
        "排1.5個月聲量"
      ]
    },
    {
      "sheet": "年約",
      "row_idx": 7,
      "col_idx": -1,
      "date": "",
      "ad_name": "",
      "spots": 720,
      "seconds": null,
      "confidence": "medium",
      "rule_used": "unit_val_extraction_v29",
      "reason": "Row 8: 發現重複數值 720 (出現 10 次), level=L2, bonus=1",
      "raw_value": 720,
      "raw_row": [
        NaN,
        NaN,
        "全家-中彰投雲林 876間＋",
        NaN,
        "每日24檔，執行15天",
        360,
        "每日24檔，執行30天",
        720,
        "每日24檔，執行30天",
        720,
        "每日24檔，執行30天",
        720,
        "每日24檔，執行30天",
        720,
        NaN,
        NaN,
        "每日24檔，執行30天",
        720,
        "每日24檔，執行30天",
        720,
        "每日24檔，執行30天",
        720,
        NaN,
        NaN,
        5400,
        NaN,
        "7月",
        1085,
        "排1.5個月聲量"
      ]
    },
    {
      "sheet": "年約",
      "row_idx": 8,
      "col_idx": -1,
      "date": "",
      "ad_name": "",
      "spots": 720,
      "seconds": null,
      "confidence": "medium",
      "rule_used": "unit_val_extraction_v29",
      "reason": "Row 9: 發現重複數值 720 (出現 10 次), level=L2, bonus=1",
      "raw_value": 720,
      "raw_row": [
        NaN,
        NaN,
        "全家-嘉義台南高雄屏東 804間",
        NaN,
        "每日24檔，執行15天",
        360,
        "每日24檔，執行30天",
        720,
        "每日24檔，執行30天",
        720,
        "每日24檔，執行30天",
        720,
        "每日24檔，執行30天",
        720,
        NaN,
        NaN,
        "每日24檔，執行30天",
        720,
        "每日24檔，執行30天",
        720,
        "每日24檔，執行30天",
        720,
        NaN,
        NaN,
        5400,
        NaN,
        "8月",
        1085,
        "排1.5個月聲量"
      ]
    },
    {
      "sheet": "年約",
      "row_idx": 9,
      "col_idx": -1,
      "date": "",
      "ad_name": "",
      "spots": 360,
      "seconds": null,
      "confidence": "medium",
      "rule_used": "unit_val_extraction_v29",
      "reason": "Row 10: 發現重複數值 360 (出現 10 次), level=L2, bonus=1",
      "raw_value": 360,
      "raw_row": [
        NaN,
        "額外\n資源\n\n回饋\n全家廣播\n4.5組\n\n+\n家樂福廣播",
        "全家-北北基 1571間",
        NaN,
        NaN,
        NaN,
        "每日12檔，執行30天",
        360,
        "每日12檔，執行30天",
        360,
        "每日12檔，執行30天",
        360,
        NaN,
        NaN,
        "每日12檔，執行30天",
        360,
        "每日12檔，執行30天",
        360,
        "每日24檔，執行30天",
        720,
        "每日12檔，執行30天",
        360,
        "每日12檔，執行30天",
        360,
        3240,
        NaN,
        "9月",
        720,
        "排1個月聲量"
      ]
    },
    {
      "sheet": "年約",
      "row_idx": 10,
      "col_idx": -1,
      "date": "",
      "ad_name": "",
      "spots": 360,
      "seconds": null,
      "confidence": "medium",
      "rule_used": "unit_val_extraction_v29",
      "reason": "Row 11: 發現重複數值 360 (出現 10 次), level=L2, bonus=1",
      "raw_value": 360,
      "raw_row": [
        NaN,
        NaN,
        "全家-桃竹苗 705間",
        NaN,
        NaN,
        NaN,
        "每日12檔，執行30天",
        360,
        "每日12檔，執行30天",
        360,
        "每日12檔，執行30天",
        360,
        NaN,
        NaN,
        "每日12檔，執行30天",
        360,
        "每日12檔，執行30天",
        360,
        "每日24檔，執行30天",
        720,
        "每日12檔，執行30天",
        360,
        "每日12檔，執行30天",
        360,
        3240,
        NaN,
        "10月",
        720,
        "排1個月聲量"
      ]
    },
    {
      "sheet": "年約",
      "row_idx": 11,
      "col_idx": -1,
      "date": "",
      "ad_name": "",
      "spots": 360,
      "seconds": null,
      "confidence": "medium",
      "rule_used": "unit_val_extraction_v29",
      "reason": "Row 12: 發現重複數值 360 (出現 9 次), level=L2, bonus=1",
      "raw_value": 360,
      "raw_row": [
        NaN,
        NaN,
        "全家-中彰投雲林 876間＋",
        NaN,
        NaN,
        NaN,
        "每日12檔，執行30天",
        360,
        "每日12檔，執行30天",
        360,
        "每日12檔，執行30天",
        360,
        NaN,
        NaN,
        "每日12檔，執行30天",
        360,
        "每日12檔，執行30天",
        360,
        "每日24檔，執行30天",
        720,
        "每日12檔，執行30天",
        360,
        "每日12檔，執行30天",
        360,
        3240,
        NaN,
        "11月",
        0,
        NaN
      ]
    },
    {
      "sheet": "年約",
      "row_idx": 12,
      "col_idx": -1,
      "date": "",
      "ad_name": "",
      "spots": 360,
      "seconds": null,
      "confidence": "medium",
      "rule_used": "unit_val_extraction_v29",
      "reason": "Row 13: 發現重複數值 360 (出現 10 次), level=L2, bonus=1",
      "raw_value": 360,
      "raw_row": [
        NaN,
        NaN,
        "全家-嘉義台南高雄屏東 804間",
        NaN,
        NaN,
        NaN,
        "每日12檔，執行30天",
        360,
        "每日12檔，執行30天",
        360,
        "每日12檔，執行30天",
        360,
        NaN,
        NaN,
        "每日12檔，執行30天",
        360,
        "每日12檔，執行30天",
        360,
        "每日24檔，執行30天",
        720,
        "每日12檔，執行30天",
        360,
        "每日12檔，執行30天",
        360,
        3240,
        NaN,
        "12月",
        720,
        "排1個月聲量"
      ]
    },
    {
      "sheet": "年約",
      "row_idx": 13,
      "col_idx": -1,
      "date": "",
      "ad_name": "",
      "spots": 210,
      "seconds": null,
      "confidence": "medium",
      "rule_used": "unit_val_extraction_v29",
      "reason": "Row 14: 發現重複數值 210 (出現 3 次), level=L2, bonus=1",
      "raw_value": 210,
      "raw_row": [
        NaN,
        NaN,
        "家樂福廣播-量販",
        NaN,
        NaN,
        NaN,
        NaN,
        NaN,
        "每日7檔，執行30天",
        210,
        "每日7檔，執行30天",
        210,
        NaN,
        NaN,
        NaN,
        NaN,
        NaN,
        NaN,
        NaN,
        NaN,
        NaN,
        NaN,
        NaN,
        NaN,
        420,
        NaN,
        NaN,
        NaN,
        NaN
      ]
    },
    {
      "sheet": "年約",
      "row_idx": 14,
      "col_idx": -1,
      "date": "",
      "ad_name": "",
      "spots": 540,
      "seconds": null,
      "confidence": "medium",
      "rule_used": "unit_val_extraction_v29",
      "reason": "Row 15: 發現重複數值 540 (出現 3 次), level=L2, bonus=1",
      "raw_value": 540,
      "raw_row": [
        NaN,
        NaN,
        "家樂福廣播-超市",
        NaN,
        NaN,
        NaN,
        NaN,
        NaN,
        "每日18檔，執行30天",
        540,
        "每日18檔，執行30天",
        540,
        NaN,
        NaN,
        NaN,
        NaN,
        NaN,
        NaN,
        NaN,
        NaN,
        NaN,
        NaN,
        NaN,
        NaN,
        1080,
        NaN,
        NaN,
        NaN,
        NaN
      ]
    },
    {
      "sheet": "年約",
      "row_idx": 15,
      "col_idx": -1,
      "date": "",
      "ad_name": "",
      "spots": 6,
      "seconds": null,
      "confidence": "medium",
      "rule_used": "unit_val_extraction_v29",
      "reason": "Row 16: 發現重複數值 6 (出現 2 次), level=L2, bonus=3",
      "raw_value": 6,
      "raw_row": [
        NaN,
        NaN,
        "廣播素材製作",
        NaN,
        "30秒素材，本專案含素材撰寫+錄音室錄音，或提供後製音檔服務，共6則素材。",
        NaN,
        NaN,
        NaN,
        NaN,
        NaN,
        NaN,
        NaN,
        NaN,
        NaN,
        NaN,
        NaN,
        NaN,
        NaN,
        NaN,
        NaN,
        NaN,
        NaN,
        NaN,
        NaN,
        6,
        NaN,
        "小計/已使用",
        5770,
        0.6678240740740741
      ]
    },
    {
      "sheet": "5月",
      "row_idx": 13,
      "col_idx": -1,
      "date": "",
      "ad_name": "",
      "spots": 30,
      "seconds": null,
      "confidence": "low",
      "rule_used": "unit_val_extraction_v29",
      "reason": "Row 14: 發現重複數值 30 (出現 13 次), level=L2, bonus=0",
      "raw_value": 30,
      "raw_row": [
        "30秒廣告",
        "企業頻道節目播放",
        "00-24",
        360,
        NaN,
        NaN,
        30,
        30,
        30,
        30,
        30,
        30,
        30,
        30,
        30,
        30,
        30,
        30,
        NaN,
        NaN,
        NaN,
        NaN,
        NaN,
        NaN,
        NaN,
        NaN,
        NaN,
        NaN,
        NaN,
        NaN,
        NaN,
        NaN,
        NaN,
        NaN,
        NaN,
        NaN,
        NaN
      ]
    },
    {
      "sheet": "5月",
      "row_idx": 15,
      "col_idx": -1,
      "date": "",
      "ad_name": "",
      "spots": 30,
      "seconds": null,
      "confidence": "low",
      "rule_used": "unit_val_extraction_v29",
      "reason": "Row 16: 發現重複數值 30 (出現 13 次), level=L2, bonus=0",
      "raw_value": 30,
      "raw_row": [
        "30秒廣告",
        "企業頻道節目播放",
        "00-24",
        360,
        NaN,
        NaN,
        30,
        30,
        30,
        30,
        30,
        30,
        30,
        30,
        30,
        30,
        30,
        30,
        NaN,
        NaN,
        NaN,
        NaN,
        NaN,
        NaN,
        NaN,
        NaN,
        NaN,
        NaN,
        NaN,
        NaN,
        NaN,
        NaN,
        NaN,
        NaN,
        NaN,
        NaN,
        NaN
      ]
    },
    {
      "sheet": "5月",
      "row_idx": 17,
      "col_idx": -1,
      "date": "",
      "ad_name": "",
      "spots": 30,
      "seconds": null,
      "confidence": "low",
      "rule_used": "unit_val_extraction_v29",
      "reason": "Row 18: 發現重複數值 30 (出現 13 次), level=L2, bonus=0",
      "raw_value": 30,
      "raw_row": [
        "30秒廣告",
        "企業頻道節目播放",
        "00-24",
        360,
        NaN,
        NaN,
        30,
        30,
        30,
        30,
        30,
        30,
        30,
        30,
        30,
        30,
        30,
        30,
        NaN,
        NaN,
        NaN,
        NaN,
        NaN,
        NaN,
        NaN,
        NaN,
        NaN,
        NaN,
        NaN,
        NaN,
        NaN,
        NaN,
        NaN,
        NaN,
        NaN,
        NaN,
        NaN
      ]
    },
    {
      "sheet": "5月",
      "row_idx": 19,
      "col_idx": -1,
      "date": "",
      "ad_name": "",
      "spots": 30,
      "seconds": null,
      "confidence": "low",
      "rule_used": "unit_val_extraction_v29",
      "reason": "Row 20: 發現重複數值 30 (出現 13 次), level=L2, bonus=0",
      "raw_value": 30,
      "raw_row": [
        "30秒廣告",
        "企業頻道節目播放",
        "00-24",
        360,
        NaN,
        NaN,
        30,
        30,
        30,
        30,
        30,
        30,
        30,
        30,
        30,
        30,
        30,
        30,
        NaN,
        NaN,
        NaN,
        NaN,
        NaN,
        NaN,
        NaN,
        NaN,
        NaN,
        NaN,
        NaN,
        NaN,
        NaN,
        NaN,
        NaN,
        NaN,
        NaN,
        NaN,
        NaN
      ]
    },
    {
      "sheet": "6月",
      "row_idx": 13,
      "col_idx": -1,
      "date": "",
      "ad_name": "",
      "spots": 40,
      "seconds": null,
      "confidence": "low",
      "rule_used": "unit_val_extraction_v29",
      "reason": "Row 14: 發現重複數值 40 (出現 28 次), level=L2, bonus=0",
      "raw_value": 40,
      "raw_row": [
        "30秒廣告",
        "企業頻道節目播放",
        "00-24",
        1080,
        NaN,
        NaN,
        40,
        40,
        40,
        40,
        40,
        40,
        40,
        40,
        40,
        40,
        40,
        40,
        40,
        40,
        40,
        40,
        40,
        40,
        40,
        40,
        40,
        40,
        40,
        40,
        40,
        40,
        40,
        NaN,
        NaN,
        NaN,
        NaN
      ]
    },
    {
      "sheet": "6月",
      "row_idx": 15,
      "col_idx": -1,
      "date": "",
      "ad_name": "",
      "spots": 40,
      "seconds": null,
      "confidence": "low",
      "rule_used": "unit_val_extraction_v29",
      "reason": "Row 16: 發現重複數值 40 (出現 28 次), level=L2, bonus=0",
      "raw_value": 40,
      "raw_row": [
        "30秒廣告",
        "企業頻道節目播放",
        "00-24",
        1080,
        NaN,
        NaN,
        40,
        40,
        40,
        40,
        40,
        40,
        40,
        40,
        40,
        40,
        40,
        40,
        40,
        40,
        40,
        40,
        40,
        40,
        40,
        40,
        40,
        40,
        40,
        40,
        40,
        40,
        40,
        NaN,
        NaN,
        NaN,
        NaN
      ]
    },
    {
      "sheet": "6月",
      "row_idx": 17,
      "col_idx": -1,
      "date": "",
      "ad_name": "",
      "spots": 40,
      "seconds": null,
      "confidence": "low",
      "rule_used": "unit_val_extraction_v29",
      "reason": "Row 18: 發現重複數值 40 (出現 28 次), level=L2, bonus=0",
      "raw_value": 40,
      "raw_row": [
        "30秒廣告",
        "企業頻道節目播放",
        "00-24",
        1080,
        NaN,
        NaN,
        40,
        40,
        40,
        40,
        40,
        40,
        40,
        40,
        40,
        40,
        40,
        40,
        40,
        40,
        40,
        40,
        40,
        40,
        40,
        40,
        40,
        40,
        40,
        40,
        40,
        40,
        40,
        NaN,
        NaN,
        NaN,
        NaN
      ]
    },
    {
      "sheet": "6月",
      "row_idx": 19,
      "col_idx": -1,
      "date": "",
      "ad_name": "",
      "spots": 40,
      "seconds": null,
      "confidence": "low",
      "rule_used": "unit_val_extraction_v29",
      "reason": "Row 20: 發現重複數值 40 (出現 28 次), level=L2, bonus=0",
      "raw_value": 40,
      "raw_row": [
        "30秒廣告",
        "企業頻道節目播放",
        "00-24",
        1080,
        NaN,
        NaN,
        40,
        40,
        40,
        40,
        40,
        40,
        40,
        40,
        40,
        40,
        40,
        40,
        40,
        40,
        40,
        40,
        40,
        40,
        40,
        40,
        40,
        40,
        40,
        40,
        40,
        40,
        40,
        NaN,
        NaN,
        NaN,
        NaN
      ]
    },
    {
      "sheet": "7月 ",
      "row_idx": 13,
      "col_idx": -1,
      "date": "",
      "ad_name": "",
      "spots": 35,
      "seconds": null,
      "confidence": "low",
      "rule_used": "unit_val_extraction_v29",
      "reason": "Row 14: 發現重複數值 35 (出現 32 次), level=L2, bonus=0",
      "raw_value": 35,
      "raw_row": [
        "30秒廣告",
        "企業頻道節目播放",
        "00-24",
        1085,
        NaN,
        NaN,
        35,
        35,
        35,
        35,
        35,
        35,
        35,
        35,
        35,
        35,
        35,
        35,
        35,
        35,
        35,
        35,
        35,
        35,
        35,
        35,
        35,
        35,
        35,
        35,
        35,
        35,
        35,
        35,
        35,
        35,
        35
      ]
    },
    {
      "sheet": "7月 ",
      "row_idx": 15,
      "col_idx": -1,
      "date": "",
      "ad_name": "",
      "spots": 35,
      "seconds": null,
      "confidence": "low",
      "rule_used": "unit_val_extraction_v29",
      "reason": "Row 16: 發現重複數值 35 (出現 32 次), level=L2, bonus=0",
      "raw_value": 35,
      "raw_row": [
        "30秒廣告",
        "企業頻道節目播放",
        "00-24",
        1085,
        NaN,
        NaN,
        35,
        35,
        35,
        35,
        35,
        35,
        35,
        35,
        35,
        35,
        35,
        35,
        35,
        35,
        35,
        35,
        35,
        35,
        35,
        35,
        35,
        35,
        35,
        35,
        35,
        35,
        35,
        35,
        35,
        35,
        35
      ]
    },
    {
      "sheet": "7月 ",
      "row_idx": 17,
      "col_idx": -1,
      "date": "",
      "ad_name": "",
      "spots": 35,
      "seconds": null,
      "confidence": "low",
      "rule_used": "unit_val_extraction_v29",
      "reason": "Row 18: 發現重複數值 35 (出現 32 次), level=L2, bonus=0",
      "raw_value": 35,
      "raw_row": [
        "30秒廣告",
        "企業頻道節目播放",
        "00-24",
        1085,
        NaN,
        NaN,
        35,
        35,
        35,
        35,
        35,
        35,
        35,
        35,
        35,
        35,
        35,
        35,
        35,
        35,
        35,
        35,
        35,
        35,
        35,
        35,
        35,
        35,
        35,
        35,
        35,
        35,
        35,
        35,
        35,
        35,
        35
      ]
    },
    {
      "sheet": "7月 ",
      "row_idx": 19,
      "col_idx": -1,
      "date": "",
      "ad_name": "",
      "spots": 35,
      "seconds": null,
      "confidence": "low",
      "rule_used": "unit_val_extraction_v29",
      "reason": "Row 20: 發現重複數值 35 (出現 32 次), level=L2, bonus=0",
      "raw_value": 35,
      "raw_row": [
        "30秒廣告",
        "企業頻道節目播放",
        "00-24",
        1085,
        NaN,
        NaN,
        35,
        35,
        35,
        35,
        35,
        35,
        35,
        35,
        35,
        35,
        35,
        35,
        35,
        35,
        35,
        35,
        35,
        35,
        35,
        35,
        35,
        35,
        35,
        35,
        35,
        35,
        35,
        35,
        35,
        35,
        35
      ]
    },
    {
      "sheet": "7月 ",
      "row_idx": 21,
      "col_idx": -1,
      "date": "",
      "ad_name": "",
      "spots": 14,
      "seconds": null,
      "confidence": "low",
      "rule_used": "unit_val_extraction_v29",
      "reason": "Row 22: 發現重複數值 14 (出現 4 次), level=L2, bonus=0",
      "raw_value": 14,
      "raw_row": [
        "量販店-30\"廣告",
        "企業頻道節目播放",
        "0900-2300",
        42,
        160650,
        198333.33333333334,
        14,
        14,
        14,
        "7/4起停檔，8/1復播",
        NaN,
        NaN,
        NaN,
        NaN,
        NaN,
        NaN,
        NaN,
        NaN,
        NaN,
        NaN,
        NaN,
        NaN,
        NaN,
        NaN,
        NaN,
        NaN,
        NaN,
        NaN,
        NaN,
        NaN,
        NaN,
        NaN,
        NaN,
        NaN,
        NaN,
        NaN,
        NaN
      ]
    },
    {
      "sheet": "7月 ",
      "row_idx": 22,
      "col_idx": -1,
      "date": "",
      "ad_name": "",
      "spots": 24,
      "seconds": null,
      "confidence": "low",
      "rule_used": "unit_val_extraction_v29",
      "reason": "Row 23: 發現重複數值 24 (出現 4 次), level=L2, bonus=0",
      "raw_value": 24,
      "raw_row": [
        "超市-30\"廣告",
        "企業頻道節目播放",
        "0000-2400",
        72,
        275400,
        NaN,
        24,
        24,
        24,
        NaN,
        NaN,
        NaN,
        NaN,
        NaN,
        NaN,
        NaN,
        NaN,
        NaN,
        NaN,
        NaN,
        NaN,
        NaN,
        NaN,
        NaN,
        NaN,
        NaN,
        NaN,
        NaN,
        NaN,
        NaN,
        NaN,
        NaN,
        NaN,
        NaN,
        NaN,
        NaN,
        NaN
      ]
    },
    {
      "sheet": "8月",
      "row_idx": 13,
      "col_idx": -1,
      "date": "",
      "ad_name": "",
      "spots": 35,
      "seconds": null,
      "confidence": "low",
      "rule_used": "unit_val_extraction_v29",
      "reason": "Row 14: 發現重複數值 35 (出現 32 次), level=L2, bonus=0",
      "raw_value": 35,
      "raw_row": [
        "30秒廣告",
        "企業頻道節目播放",
        "00-24",
        1085,
        NaN,
        NaN,
        35,
        35,
        35,
        35,
        35,
        35,
        35,
        35,
        35,
        35,
        35,
        35,
        35,
        35,
        35,
        35,
        35,
        35,
        35,
        35,
        35,
        35,
        35,
        35,
        35,
        35,
        35,
        35,
        35,
        35,
        35
      ]
    },
    {
      "sheet": "8月",
      "row_idx": 15,
      "col_idx": -1,
      "date": "",
      "ad_name": "",
      "spots": 35,
      "seconds": null,
      "confidence": "low",
      "rule_used": "unit_val_extraction_v29",
      "reason": "Row 16: 發現重複數值 35 (出現 32 次), level=L2, bonus=0",
      "raw_value": 35,
      "raw_row": [
        "30秒廣告",
        "企業頻道節目播放",
        "00-24",
        1085,
        NaN,
        NaN,
        35,
        35,
        35,
        35,
        35,
        35,
        35,
        35,
        35,
        35,
        35,
        35,
        35,
        35,
        35,
        35,
        35,
        35,
        35,
        35,
        35,
        35,
        35,
        35,
        35,
        35,
        35,
        35,
        35,
        35,
        35
      ]
    },
    {
      "sheet": "8月",
      "row_idx": 17,
      "col_idx": -1,
      "date": "",
      "ad_name": "",
      "spots": 35,
      "seconds": null,
      "confidence": "low",
      "rule_used": "unit_val_extraction_v29",
      "reason": "Row 18: 發現重複數值 35 (出現 32 次), level=L2, bonus=0",
      "raw_value": 35,
      "raw_row": [
        "30秒廣告",
        "企業頻道節目播放",
        "00-24",
        1085,
        NaN,
        NaN,
        35,
        35,
        35,
        35,
        35,
        35,
        35,
        35,
        35,
        35,
        35,
        35,
        35,
        35,
        35,
        35,
        35,
        35,
        35,
        35,
        35,
        35,
        35,
        35,
        35,
        35,
        35,
        35,
        35,
        35,
        35
      ]
    },
    {
      "sheet": "8月",
      "row_idx": 19,
      "col_idx": -1,
      "date": "",
      "ad_name": "",
      "spots": 35,
      "seconds": null,
      "confidence": "low",
      "rule_used": "unit_val_extraction_v29",
      "reason": "Row 20: 發現重複數值 35 (出現 32 次), level=L2, bonus=0",
      "raw_value": 35,
      "raw_row": [
        "30秒廣告",
        "企業頻道節目播放",
        "00-24",
        1085,
        NaN,
        NaN,
        35,
        35,
        35,
        35,
        35,
        35,
        35,
        35,
        35,
        35,
        35,
        35,
        35,
        35,
        35,
        35,
        35,
        35,
        35,
        35,
        35,
        35,
        35,
        35,
        35,
        35,
        35,
        35,
        35,
        35,
        35
      ]
    },
    {
      "sheet": "8月",
      "row_idx": 21,
      "col_idx": -1,
      "date": "",
      "ad_name": "",
      "spots": 14,
      "seconds": null,
      "confidence": "low",
      "rule_used": "unit_val_extraction_v29",
      "reason": "Row 22: 發現重複數值 14 (出現 32 次), level=L2, bonus=0",
      "raw_value": 14,
      "raw_row": [
        "量販店-30\"廣告",
        "企業頻道節目播放",
        "0900-2300",
        434,
        1660050,
        NaN,
        14,
        14,
        14,
        14,
        14,
        14,
        14,
        14,
        14,
        14,
        14,
        14,
        14,
        14,
        14,
        14,
        14,
        14,
        14,
        14,
        14,
        14,
        14,
        14,
        14,
        14,
        14,
        14,
        14,
        14,
        14
      ]
    },
    {
      "sheet": "8月",
      "row_idx": 22,
      "col_idx": -1,
      "date": "",
      "ad_name": "",
      "spots": 24,
      "seconds": null,
      "confidence": "low",
      "rule_used": "unit_val_extraction_v29",
      "reason": "Row 23: 發現重複數值 24 (出現 32 次), level=L2, bonus=0",
      "raw_value": 24,
      "raw_row": [
        "超市-30\"廣告",
        "企業頻道節目播放",
        "0000-2400",
        744,
        2845800,
        NaN,
        24,
        24,
        24,
        24,
        24,
        24,
        24,
        24,
        24,
        24,
        24,
        24,
        24,
        24,
        24,
        24,
        24,
        24,
        24,
        24,
        24,
        24,
        24,
        24,
        24,
        24,
        24,
        24,
        24,
        24,
        24
      ]
    },
    {
      "sheet": "9月 ",
      "row_idx": 13,
      "col_idx": -1,
      "date": "",
      "ad_name": "",
      "spots": 24,
      "seconds": null,
      "confidence": "low",
      "rule_used": "unit_val_extraction_v29",
      "reason": "Row 14: 發現重複數值 24 (出現 31 次), level=L2, bonus=0",
      "raw_value": 24,
      "raw_row": [
        "30秒廣告",
        "企業頻道節目播放",
        "00-24",
        720,
        NaN,
        NaN,
        24,
        24,
        24,
        24,
        24,
        24,
        24,
        24,
        24,
        24,
        24,
        24,
        24,
        24,
        24,
        24,
        24,
        24,
        24,
        24,
        24,
        24,
        24,
        24,
        24,
        24,
        24,
        24,
        24,
        24,
        NaN
      ]
    },
    {
      "sheet": "9月 ",
      "row_idx": 15,
      "col_idx": -1,
      "date": "",
      "ad_name": "",
      "spots": 24,
      "seconds": null,
      "confidence": "low",
      "rule_used": "unit_val_extraction_v29",
      "reason": "Row 16: 發現重複數值 24 (出現 31 次), level=L2, bonus=0",
      "raw_value": 24,
      "raw_row": [
        "30秒廣告",
        "企業頻道節目播放",
        "00-24",
        720,
        NaN,
        NaN,
        24,
        24,
        24,
        24,
        24,
        24,
        24,
        24,
        24,
        24,
        24,
        24,
        24,
        24,
        24,
        24,
        24,
        24,
        24,
        24,
        24,
        24,
        24,
        24,
        24,
        24,
        24,
        24,
        24,
        24,
        NaN
      ]
    },
    {
      "sheet": "9月 ",
      "row_idx": 17,
      "col_idx": -1,
      "date": "",
      "ad_name": "",
      "spots": 24,
      "seconds": null,
      "confidence": "low",
      "rule_used": "unit_val_extraction_v29",
      "reason": "Row 18: 發現重複數值 24 (出現 31 次), level=L2, bonus=0",
      "raw_value": 24,
      "raw_row": [
        "30秒廣告",
        "企業頻道節目播放",
        "00-24",
        720,
        NaN,
        NaN,
        24,
        24,
        24,
        24,
        24,
        24,
        24,
        24,
        24,
        24,
        24,
        24,
        24,
        24,
        24,
        24,
        24,
        24,
        24,
        24,
        24,
        24,
        24,
        24,
        24,
        24,
        24,
        24,
        24,
        24,
        NaN
      ]
    },
    {
      "sheet": "9月 ",
      "row_idx": 19,
      "col_idx": -1,
      "date": "",
      "ad_name": "",
      "spots": 24,
      "seconds": null,
      "confidence": "low",
      "rule_used": "unit_val_extraction_v29",
      "reason": "Row 20: 發現重複數值 24 (出現 31 次), level=L2, bonus=0",
      "raw_value": 24,
      "raw_row": [
        "30秒廣告",
        "企業頻道節目播放",
        "00-24",
        720,
        NaN,
        NaN,
        24,
        24,
        24,
        24,
        24,
        24,
        24,
        24,
        24,
        24,
        24,
        24,
        24,
        24,
        24,
        24,
        24,
        24,
        24,
        24,
        24,
        24,
        24,
        24,
        24,
        24,
        24,
        24,
        24,
        24,
        NaN
      ]
    },
    {
      "sheet": "10月",
      "row_idx": 13,
      "col_idx": -1,
      "date": "",
      "ad_name": "",
      "spots": 24,
      "seconds": null,
      "confidence": "low",
      "rule_used": "unit_val_extraction_v29",
      "reason": "Row 14: 發現重複數值 24 (出現 32 次), level=L2, bonus=0",
      "raw_value": 24,
      "raw_row": [
        "30秒廣告",
        "企業頻道節目播放",
        "00-24",
        744,
        NaN,
        NaN,
        24,
        24,
        24,
        24,
        24,
        24,
        24,
        24,
        24,
        24,
        24,
        24,
        24,
        24,
        24,
        24,
        24,
        24,
        24,
        24,
        24,
        24,
        24,
        24,
        24,
        24,
        24,
        24,
        24,
        24,
        24
      ]
    },
    {
      "sheet": "10月",
      "row_idx": 15,
      "col_idx": -1,
      "date": "",
      "ad_name": "",
      "spots": 24,
      "seconds": null,
      "confidence": "low",
      "rule_used": "unit_val_extraction_v29",
      "reason": "Row 16: 發現重複數值 24 (出現 32 次), level=L2, bonus=0",
      "raw_value": 24,
      "raw_row": [
        "30秒廣告",
        "企業頻道節目播放",
        "00-24",
        744,
        NaN,
        NaN,
        24,
        24,
        24,
        24,
        24,
        24,
        24,
        24,
        24,
        24,
        24,
        24,
        24,
        24,
        24,
        24,
        24,
        24,
        24,
        24,
        24,
        24,
        24,
        24,
        24,
        24,
        24,
        24,
        24,
        24,
        24
      ]
    },
    {
      "sheet": "10月",
      "row_idx": 17,
      "col_idx": -1,
      "date": "",
      "ad_name": "",
      "spots": 24,
      "seconds": null,
      "confidence": "low",
      "rule_used": "unit_val_extraction_v29",
      "reason": "Row 18: 發現重複數值 24 (出現 32 次), level=L2, bonus=0",
      "raw_value": 24,
      "raw_row": [
        "30秒廣告",
        "企業頻道節目播放",
        "00-24",
        744,
        NaN,
        NaN,
        24,
        24,
        24,
        24,
        24,
        24,
        24,
        24,
        24,
        24,
        24,
        24,
        24,
        24,
        24,
        24,
        24,
        24,
        24,
        24,
        24,
        24,
        24,
        24,
        24,
        24,
        24,
        24,
        24,
        24,
        24
      ]
    },
    {
      "sheet": "10月",
      "row_idx": 19,
      "col_idx": -1,
      "date": "",
      "ad_name": "",
      "spots": 24,
      "seconds": null,
      "confidence": "low",
      "rule_used": "unit_val_extraction_v29",
      "reason": "Row 20: 發現重複數值 24 (出現 32 次), level=L2, bonus=0",
      "raw_value": 24,
      "raw_row": [
        "30秒廣告",
        "企業頻道節目播放",
        "00-24",
        744,
        NaN,
        NaN,
        24,
        24,
        24,
        24,
        24,
        24,
        24,
        24,
        24,
        24,
        24,
        24,
        24,
        24,
        24,
        24,
        24,
        24,
        24,
        24,
        24,
        24,
        24,
        24,
        24,
        24,
        24,
        24,
        24,
        24,
        24
      ]
    },
    {
      "sheet": "12月",
      "row_idx": 13,
      "col_idx": -1,
      "date": "",
      "ad_name": "",
      "spots": 24,
      "seconds": null,
      "confidence": "low",
      "rule_used": "unit_val_extraction_v29",
      "reason": "Row 14: 發現重複數值 24 (出現 32 次), level=L2, bonus=0",
      "raw_value": 24,
      "raw_row": [
        "30秒廣告",
        "企業頻道節目播放",
        "00-24",
        744,
        NaN,
        NaN,
        24,
        24,
        24,
        24,
        24,
        24,
        24,
        24,
        24,
        24,
        24,
        24,
        24,
        24,
        24,
        24,
        24,
        24,
        24,
        24,
        24,
        24,
        24,
        24,
        24,
        24,
        24,
        24,
        24,
        24,
        24
      ]
    },
    {
      "sheet": "12月",
      "row_idx": 15,
      "col_idx": -1,
      "date": "",
      "ad_name": "",
      "spots": 24,
      "seconds": null,
      "confidence": "low",
      "rule_used": "unit_val_extraction_v29",
      "reason": "Row 16: 發現重複數值 24 (出現 32 次), level=L2, bonus=0",
      "raw_value": 24,
      "raw_row": [
        "30秒廣告",
        "企業頻道節目播放",
        "00-24",
        744,
        NaN,
        NaN,
        24,
        24,
        24,
        24,
        24,
        24,
        24,
        24,
        24,
        24,
        24,
        24,
        24,
        24,
        24,
        24,
        24,
        24,
        24,
        24,
        24,
        24,
        24,
        24,
        24,
        24,
        24,
        24,
        24,
        24,
        24
      ]
    },
    {
      "sheet": "12月",
      "row_idx": 17,
      "col_idx": -1,
      "date": "",
      "ad_name": "",
      "spots": 24,
      "seconds": null,
      "confidence": "low",
      "rule_used": "unit_val_extraction_v29",
      "reason": "Row 18: 發現重複數值 24 (出現 32 次), level=L2, bonus=0",
      "raw_value": 24,
      "raw_row": [
        "30秒廣告",
        "企業頻道節目播放",
        "00-24",
        744,
        NaN,
        NaN,
        24,
        24,
        24,
        24,
        24,
        24,
        24,
        24,
        24,
        24,
        24,
        24,
        24,
        24,
        24,
        24,
        24,
        24,
        24,
        24,
        24,
        24,
        24,
        24,
        24,
        24,
        24,
        24,
        24,
        24,
        24
      ]
    },
    {
      "sheet": "12月",
      "row_idx": 19,
      "col_idx": -1,
      "date": "",
      "ad_name": "",
      "spots": 24,
      "seconds": null,
      "confidence": "low",
      "rule_used": "unit_val_extraction_v29",
      "reason": "Row 20: 發現重複數值 24 (出現 32 次), level=L2, bonus=0",
      "raw_value": 24,
      "raw_row": [
        "30秒廣告",
        "企業頻道節目播放",
        "00-24",
        744,
        NaN,
        NaN,
        24,
        24,
        24,
        24,
        24,
        24,
        24,
        24,
        24,
        24,
        24,
        24,
        24,
        24,
        24,
        24,
        24,
        24,
        24,
        24,
        24,
        24,
        24,
        24,
        24,
        24,
        24,
        24,
        24,
        24,
        24
      ]
    },
    {
      "sheet": "1月",
      "row_idx": 10,
      "col_idx": -1,
      "date": "",
      "ad_name": "",
      "spots": 24,
      "seconds": null,
      "confidence": "low",
      "rule_used": "unit_val_extraction_v29",
      "reason": "Row 11: 發現重複數值 24 (出現 32 次), level=L2, bonus=0",
      "raw_value": 24,
      "raw_row": [
        "30秒廣告",
        "企業頻道節目播放",
        "00-24",
        744,
        NaN,
        NaN,
        24,
        24,
        24,
        24,
        24,
        24,
        24,
        24,
        24,
        24,
        24,
        24,
        24,
        24,
        24,
        24,
        24,
        24,
        24,
        24,
        24,
        24,
        24,
        24,
        24,
        24,
        24,
        24,
        24,
        24,
        24,
        NaN,
        NaN,
        NaN
      ]
    },
    {
      "sheet": "1月",
      "row_idx": 12,
      "col_idx": -1,
      "date": "",
      "ad_name": "",
      "spots": 24,
      "seconds": null,
      "confidence": "low",
      "rule_used": "unit_val_extraction_v29",
      "reason": "Row 13: 發現重複數值 24 (出現 32 次), level=L2, bonus=0",
      "raw_value": 24,
      "raw_row": [
        "30秒廣告",
        "企業頻道節目播放",
        "00-24",
        744,
        NaN,
        NaN,
        24,
        24,
        24,
        24,
        24,
        24,
        24,
        24,
        24,
        24,
        24,
        24,
        24,
        24,
        24,
        24,
        24,
        24,
        24,
        24,
        24,
        24,
        24,
        24,
        24,
        24,
        24,
        24,
        24,
        24,
        24,
        NaN,
        NaN,
        NaN
      ]
    },
    {
      "sheet": "1月",
      "row_idx": 14,
      "col_idx": -1,
      "date": "",
      "ad_name": "",
      "spots": 24,
      "seconds": null,
      "confidence": "low",
      "rule_used": "unit_val_extraction_v29",
      "reason": "Row 15: 發現重複數值 24 (出現 32 次), level=L2, bonus=0",
      "raw_value": 24,
      "raw_row": [
        "30秒廣告",
        "企業頻道節目播放",
        "00-24",
        744,
        NaN,
        NaN,
        24,
        24,
        24,
        24,
        24,
        24,
        24,
        24,
        24,
        24,
        24,
        24,
        24,
        24,
        24,
        24,
        24,
        24,
        24,
        24,
        24,
        24,
        24,
        24,
        24,
        24,
        24,
        24,
        24,
        24,
        24,
        NaN,
        NaN,
        NaN
      ]
    },
    {
      "sheet": "1月",
      "row_idx": 16,
      "col_idx": -1,
      "date": "",
      "ad_name": "",
      "spots": 24,
      "seconds": null,
      "confidence": "low",
      "rule_used": "unit_val_extraction_v29",
      "reason": "Row 17: 發現重複數值 24 (出現 32 次), level=L2, bonus=0",
      "raw_value": 24,
      "raw_row": [
        "30秒廣告",
        "企業頻道節目播放",
        "00-24",
        744,
        NaN,
        NaN,
        24,
        24,
        24,
        24,
        24,
        24,
        24,
        24,
        24,
        24,
        24,
        24,
        24,
        24,
        24,
        24,
        24,
        24,
        24,
        24,
        24,
        24,
        24,
        24,
        24,
        24,
        24,
        24,
        24,
        24,
        24,
        NaN,
        NaN,
        NaN
      ]
    },
    {
      "sheet": "1月",
      "row_idx": 18,
      "col_idx": -1,
      "date": "",
      "ad_name": "",
      "spots": 14,
      "seconds": null,
      "confidence": "low",
      "rule_used": "unit_val_extraction_v29",
      "reason": "Row 19: 發現重複數值 14 (出現 16 次), level=L2, bonus=0",
      "raw_value": 14,
      "raw_row": [
        "量販店-30\"廣告",
        "企業頻道節目播放",
        "0900-2300",
        210,
        803250,
        NaN,
        NaN,
        NaN,
        NaN,
        NaN,
        NaN,
        NaN,
        NaN,
        NaN,
        NaN,
        NaN,
        NaN,
        NaN,
        NaN,
        NaN,
        NaN,
        NaN,
        14,
        14,
        14,
        14,
        14,
        14,
        14,
        14,
        14,
        14,
        14,
        14,
        14,
        14,
        14,
        NaN,
        NaN,
        NaN
      ]
    },
    {
      "sheet": "1月",
      "row_idx": 19,
      "col_idx": -1,
      "date": "",
      "ad_name": "",
      "spots": 24,
      "seconds": null,
      "confidence": "low",
      "rule_used": "unit_val_extraction_v29",
      "reason": "Row 20: 發現重複數值 24 (出現 16 次), level=L2, bonus=0",
      "raw_value": 24,
      "raw_row": [
        "超市-30\"廣告",
        "企業頻道節目播放",
        "0000-2400",
        360,
        1377000,
        NaN,
        NaN,
        NaN,
        NaN,
        NaN,
        NaN,
        NaN,
        NaN,
        NaN,
        NaN,
        NaN,
        NaN,
        NaN,
        NaN,
        NaN,
        NaN,
        NaN,
        24,
        24,
        24,
        24,
        24,
        24,
        24,
        24,
        24,
        24,
        24,
        24,
        24,
        24,
        24,
        NaN,
        NaN,
        NaN
      ]
    },
    {
      "sheet": "2月 ",
      "row_idx": 10,
      "col_idx": -1,
      "date": "",
      "ad_name": "",
      "spots": 24,
      "seconds": null,
      "confidence": "low",
      "rule_used": "unit_val_extraction_v29",
      "reason": "Row 11: 發現重複數值 24 (出現 29 次), level=L2, bonus=0",
      "raw_value": 24,
      "raw_row": [
        "30秒廣告",
        "企業頻道節目播放",
        "00-24",
        672,
        NaN,
        NaN,
        24,
        24,
        24,
        24,
        24,
        24,
        24,
        24,
        24,
        24,
        24,
        24,
        24,
        24,
        24,
        24,
        24,
        24,
        24,
        24,
        24,
        24,
        24,
        24,
        24,
        24,
        24,
        24,
        NaN,
        NaN,
        NaN,
        NaN,
        NaN,
        NaN
      ]
    },
    {
      "sheet": "2月 ",
      "row_idx": 12,
      "col_idx": -1,
      "date": "",
      "ad_name": "",
      "spots": 24,
      "seconds": null,
      "confidence": "low",
      "rule_used": "unit_val_extraction_v29",
      "reason": "Row 13: 發現重複數值 24 (出現 29 次), level=L2, bonus=0",
      "raw_value": 24,
      "raw_row": [
        "30秒廣告",
        "企業頻道節目播放",
        "00-24",
        672,
        NaN,
        NaN,
        24,
        24,
        24,
        24,
        24,
        24,
        24,
        24,
        24,
        24,
        24,
        24,
        24,
        24,
        24,
        24,
        24,
        24,
        24,
        24,
        24,
        24,
        24,
        24,
        24,
        24,
        24,
        24,
        NaN,
        NaN,
        NaN,
        NaN,
        NaN,
        NaN
      ]
    },
    {
      "sheet": "2月 ",
      "row_idx": 14,
      "col_idx": -1,
      "date": "",
      "ad_name": "",
      "spots": 24,
      "seconds": null,
      "confidence": "low",
      "rule_used": "unit_val_extraction_v29",
      "reason": "Row 15: 發現重複數值 24 (出現 29 次), level=L2, bonus=0",
      "raw_value": 24,
      "raw_row": [
        "30秒廣告",
        "企業頻道節目播放",
        "00-24",
        672,
        NaN,
        NaN,
        24,
        24,
        24,
        24,
        24,
        24,
        24,
        24,
        24,
        24,
        24,
        24,
        24,
        24,
        24,
        24,
        24,
        24,
        24,
        24,
        24,
        24,
        24,
        24,
        24,
        24,
        24,
        24,
        NaN,
        NaN,
        NaN,
        NaN,
        NaN,
        NaN
      ]
    },
    {
      "sheet": "2月 ",
      "row_idx": 16,
      "col_idx": -1,
      "date": "",
      "ad_name": "",
      "spots": 24,
      "seconds": null,
      "confidence": "low",
      "rule_used": "unit_val_extraction_v29",
      "reason": "Row 17: 發現重複數值 24 (出現 29 次), level=L2, bonus=0",
      "raw_value": 24,
      "raw_row": [
        "30秒廣告",
        "企業頻道節目播放",
        "00-24",
        672,
        NaN,
        NaN,
        24,
        24,
        24,
        24,
        24,
        24,
        24,
        24,
        24,
        24,
        24,
        24,
        24,
        24,
        24,
        24,
        24,
        24,
        24,
        24,
        24,
        24,
        24,
        24,
        24,
        24,
        24,
        24,
        NaN,
        NaN,
        NaN,
        NaN,
        NaN,
        NaN
      ]
    },
    {
      "sheet": "2月 ",
      "row_idx": 18,
      "col_idx": -1,
      "date": "",
      "ad_name": "",
      "spots": 14,
      "seconds": null,
      "confidence": "low",
      "rule_used": "unit_val_extraction_v29",
      "reason": "Row 19: 發現重複數值 14 (出現 16 次), level=L2, bonus=0",
      "raw_value": 14,
      "raw_row": [
        "量販店-30\"廣告",
        "企業頻道節目播放",
        "0900-2300",
        210,
        803250,
        NaN,
        14,
        14,
        14,
        14,
        14,
        14,
        14,
        14,
        14,
        14,
        14,
        14,
        14,
        14,
        14,
        NaN,
        NaN,
        NaN,
        NaN,
        NaN,
        NaN,
        NaN,
        NaN,
        NaN,
        NaN,
        NaN,
        NaN,
        NaN,
        NaN,
        NaN,
        NaN,
        NaN,
        NaN,
        NaN
      ]
    },
    {
      "sheet": "2月 ",
      "row_idx": 19,
      "col_idx": -1,
      "date": "",
      "ad_name": "",
      "spots": 24,
      "seconds": null,
      "confidence": "low",
      "rule_used": "unit_val_extraction_v29",
      "reason": "Row 20: 發現重複數值 24 (出現 16 次), level=L2, bonus=0",
      "raw_value": 24,
      "raw_row": [
        "超市-30\"廣告",
        "企業頻道節目播放",
        "0000-2400",
        360,
        1377000,
        NaN,
        24,
        24,
        24,
        24,
        24,
        24,
        24,
        24,
        24,
        24,
        24,
        24,
        24,
        24,
        24,
        NaN,
        NaN,
        NaN,
        NaN,
        NaN,
        NaN,
        NaN,
        NaN,
        NaN,
        NaN,
        NaN,
        NaN,
        NaN,
        NaN,
        NaN,
        NaN,
        NaN,
        NaN,
        NaN
      ]
    }
  ],
  "human_corrections": [],
  "created_at": "2026-01-28 00:38:28"
}