{
  "file_hash": "611ed04e32f532262c77f057e4e16969",
  "file_name": "50_文化總會-我們的除夕夜0119-0216-全家.xlsx",
  "rid": "50",
  "ai_interpretations": [
    {
      "sheet": "中華文化總會",
      "row_idx": 11,
      "col_idx": -1,
      "date": "",
      "ad_name": "",
      "spots": 8,
      "seconds": null,
      "confidence": "low",
      "rule_used": "unit_val_extraction_v29",
      "reason": "Row 12: 發現重複數值 8 (出現 30 次), level=L2, bonus=0",
      "raw_value": 8,
      "raw_row": [
        "30秒廣告",
        "企業頻道節目播放",
        "06:00-23:59",
        232,
        NaN,
        NaN,
        8,
        8,
        8,
        8,
        8,
        8,
        8,
        8,
        8,
        8,
        8,
        8,
        8,
        8,
        8,
        8,
        8,
        8,
        8,
        8,
        8,
        8,
        8,
        8,
        8,
        8,
        8,
        8,
        8,
        NaN,
        103111.11111111111
      ]
    },
    {
      "sheet": "中華文化總會",
      "row_idx": 13,
      "col_idx": -1,
      "date": "",
      "ad_name": "",
      "spots": 8,
      "seconds": null,
      "confidence": "low",
      "rule_used": "unit_val_extraction_v29",
      "reason": "Row 14: 發現重複數值 8 (出現 30 次), level=L2, bonus=0",
      "raw_value": 8,
      "raw_row": [
        "30秒廣告",
        "企業頻道節目播放",
        "06:00-23:59",
        232,
        NaN,
        NaN,
        8,
        8,
        8,
        8,
        8,
        8,
        8,
        8,
        8,
        8,
        8,
        8,
        8,
        8,
        8,
        8,
        8,
        8,
        8,
        8,
        8,
        8,
        8,
        8,
        8,
        8,
        8,
        8,
        8,
        NaN,
        108266.66666666667
      ]
    },
    {
      "sheet": "中華文化總會",
      "row_idx": 15,
      "col_idx": -1,
      "date": "",
      "ad_name": "",
      "spots": 8,
      "seconds": null,
      "confidence": "low",
      "rule_used": "unit_val_extraction_v29",
      "reason": "Row 16: 發現重複數值 8 (出現 30 次), level=L2, bonus=0",
      "raw_value": 8,
      "raw_row": [
        "30秒廣告",
        "企業頻道節目播放",
        "06:00-23:59",
        232,
        NaN,
        NaN,
        8,
        8,
        8,
        8,
        8,
        8,
        8,
        8,
        8,
        8,
        8,
        8,
        8,
        8,
        8,
        8,
        8,
        8,
        8,
        8,
        8,
        8,
        8,
        8,
        8,
        8,
        8,
        8,
        8,
        NaN,
        NaN
      ]
    },
    {
      "sheet": "中華文化總會",
      "row_idx": 17,
      "col_idx": -1,
      "date": "",
      "ad_name": "",
      "spots": 8,
      "seconds": null,
      "confidence": "low",
      "rule_used": "unit_val_extraction_v29",
      "reason": "Row 18: 發現重複數值 8 (出現 30 次), level=L2, bonus=0",
      "raw_value": 8,
      "raw_row": [
        "30秒廣告",
        "企業頻道節目播放",
        "06:00-23:59",
        232,
        NaN,
        NaN,
        8,
        8,
        8,
        8,
        8,
        8,
        8,
        8,
        8,
        8,
        8,
        8,
        8,
        8,
        8,
        8,
        8,
        8,
        8,
        8,
        8,
        8,
        8,
        8,
        8,
        8,
        8,
        8,
        8,
        NaN,
        NaN
      ]
    },
    {
      "sheet": "中華文化總會",
      "row_idx": 18,
      "col_idx": -1,
      "date": "",
      "ad_name": "",
      "spots": 32,
      "seconds": null,
      "confidence": "low",
      "rule_used": "unit_val_extraction_v29",
      "reason": "Row 19: 發現重複數值 32 (出現 29 次), level=L3, bonus=-2",
      "raw_value": 32,
      "raw_row": [
        "每日播出總檔次  ",
        NaN,
        NaN,
        NaN,
        NaN,
        NaN,
        32,
        32,
        32,
        32,
        32,
        32,
        32,
        32,
        32,
        32,
        32,
        32,
        32,
        32,
        32,
        32,
        32,
        32,
        32,
        32,
        32,
        32,
        32,
        32,
        32,
        32,
        32,
        32,
        32,
        0,
        NaN
      ]
    }
  ],
  "human_corrections": [],
  "created_at": "2026-01-28 00:38:59"
}